.gitignore
.travis.yml
LICENSE
README.md
setup.py
examples/businterfaces.xml
examples/gen_c_header.py
examples/gen_markdown.py
examples/generic_example.xml
examples/ipxactwriter.py
examples/print_businterfaces.py
examples/print_filesets.py
examples/selftest.sh
examples/write_xml.py
golden/bus.txt
golden/files.txt
golden/ipxactwriter.xml
golden/ipxactwriter2.xml
golden/new.xml
golden/new2.xml
golden/out.h
golden/out.md
golden/write_xml.txt
ipyxact/__init__.py
ipyxact/ipxact2014.py
ipyxact/ipxact2v.py
ipyxact/ipxact_yaml.py
ipyxact/ipyxact.py
ipyxact/verilogwriter.py
ipyxact.egg-info/PKG-INFO
ipyxact.egg-info/SOURCES.txt
ipyxact.egg-info/dependency_links.txt
ipyxact.egg-info/entry_points.txt
ipyxact.egg-info/requires.txt
ipyxact.egg-info/top_level.txt
tests/unit/IpxactInt.py