Metadata-Version: 2.1
Name: ipyxact
Version: 0.3.1
Summary: Python IP-Xact handling library
Home-page: https://github.com/olofk/ipyxact
Author: Olof Kindgren
Author-email: olof.kindgren@gmail.com
License: MIT
Keywords: ipxact IP-Xact HDL ASIC FPGA
Platform: UNKNOWN
Classifier: Development Status :: 3 - Alpha
Classifier: Environment :: Console
Classifier: Intended Audience :: Developers
Classifier: License :: OSI Approved :: MIT License
Classifier: Natural Language :: English
Classifier: Operating System :: OS Independent
Classifier: Programming Language :: Python
Classifier: Topic :: Scientific/Engineering :: Electronic Design Automation (EDA)
License-File: LICENSE
